pygimbal/__init__.py
pygimbal/control.py
pygimbal-1.0.0.dist-info/LICENSE
pygimbal-1.0.0.dist-info/METADATA
pygimbal-1.0.0.dist-info/WHEEL
pygimbal-1.0.0.dist-info/top_level.txt
pygimbal-1.0.0.dist-info/zip-safe
pygimbal-1.0.0.dist-info/RECORD
