Metadata-Version: 2.1
Name: pygimbal
Version: 1.0.0
Summary: Python sample control gimbal via Mavlink.
Home-page: https://github.com/winter2897/pygimbal
Author: winter2897
Author-email: haiquantran2897@gmail.com
License: LGPLv3
Classifier: Development Status :: 5 - Production/Stable
Classifier: Environment :: Console
Classifier: Intended Audience :: Science/Research
Classifier: License :: OSI Approved :: GNU Lesser General Public License v3 (LGPLv3)
Classifier: Operating System :: OS Independent
Classifier: Programming Language :: Python :: 3
Classifier: Topic :: Scientific/Engineering
License-File: LICENSE
Requires-Dist: pymavlink (>=2.2.20)
